Topsis_Shikhar_101917064/__init__.py
Topsis_Shikhar_101917064-1.2.7.dist-info/LICENSE
Topsis_Shikhar_101917064-1.2.7.dist-info/METADATA
Topsis_Shikhar_101917064-1.2.7.dist-info/WHEEL
Topsis_Shikhar_101917064-1.2.7.dist-info/entry_points.txt
Topsis_Shikhar_101917064-1.2.7.dist-info/top_level.txt
Topsis_Shikhar_101917064-1.2.7.dist-info/RECORD
