Metadata-Version: 2.1
Name: Topsis-Shikhar-101917064
Version: 1.2.7
Summary: A Python package implementing TOPSIS technique.
Home-page: UNKNOWN
Author: Shikhar Garg
Author-email: shikhargarg15@gmail.com
License: MIT
Platform: UNKNOWN
Classifier: License :: OSI Approved :: MIT License
Classifier: Programming Language :: Python :: 3.7
Classifier: Programming Language :: Python :: 3.9
License-File: LICENSE
Requires-Dist: pandas
